diffio/__init__.py
diffio/client.py
diffio/errors.py
diffio/testing.py
diffio/types.py
diffio-0.1.6.dist-info/licenses/LICENSE
diffio-0.1.6.dist-info/METADATA
diffio-0.1.6.dist-info/WHEEL
diffio-0.1.6.dist-info/top_level.txt
diffio-0.1.6.dist-info/RECORD
